lxmlasdict/__init__.py
lxmlasdict/base.py
lxmlasdict/utils.py
lxmlasdict-0.1.0.dist-info/LICENSE
lxmlasdict-0.1.0.dist-info/METADATA
lxmlasdict-0.1.0.dist-info/WHEEL
lxmlasdict-0.1.0.dist-info/top_level.txt
lxmlasdict-0.1.0.dist-info/RECORD
