Metadata-Version: 2.1
Name: lxmlasdict
Version: 0.1.0
Summary: "lxmlasdict" allows you to treat lxml tree elements as if you were working with a dict
Home-page: https://github.com/nazarkhanov/lxmlasdict
Author: Alisher Nazarkhanov
Author-email: alisher.nazarkhanov.dev@gmail.com
License: MIT
Platform: UNKNOWN
Classifier: Development Status :: 4 - Beta
Classifier: Intended Audience :: Developers
Classifier: License :: OSI Approved :: MIT License
Classifier: Programming Language :: Python :: 3.10
Classifier: Topic :: Text Processing :: Markup :: XML
License-File: LICENSE
Requires-Dist: lxml ==4.9.3
